{
	"backtraceGraph" : 
	{
		"commands" : 
		[
			"install"
		],
		"files" : 
		[
			"vnproglib-1.2.0.0/cpp/CMakeLists.txt"
		],
		"nodes" : 
		[
			{
				"file" : 0
			},
			{
				"command" : 0,
				"file" : 0,
				"line" : 44,
				"parent" : 0
			},
			{
				"command" : 0,
				"file" : 0,
				"line" : 49,
				"parent" : 0
			}
		]
	},
	"installers" : 
	[
		{
			"backtrace" : 1,
			"component" : "Unspecified",
			"destination" : "lib",
			"paths" : 
			[
				"vnproglib-1.2.0.0/cpp/libvncxx.so"
			],
			"targetId" : "vncxx::@e06fe4551d8b7f1f2067",
			"targetIndex" : 4,
			"type" : "target"
		},
		{
			"backtrace" : 2,
			"component" : "Unspecified",
			"destination" : "include",
			"paths" : 
			[
				"vnproglib-1.2.0.0/cpp/include/vn"
			],
			"type" : "directory"
		}
	],
	"paths" : 
	{
		"build" : "vnproglib-1.2.0.0/cpp",
		"source" : "vnproglib-1.2.0.0/cpp"
	}
}
